{
  "ticker": "TSLA",
  "generated_at_utc": "2026-06-23T01:31:03.592663+00:00",
  "last_known_date": "2026-06-22",
  "last_known_price": 405.05,
  "test_mae_return": 0.06436,
  "forecast": [
    {
      "date": "2026-06-23",
      "day": 1,
      "predicted_price": 403.87,
      "predicted_return_pct": -0.291,
      "change_from_last_pct": -0.29
    },
    {
      "date": "2026-06-24",
      "day": 2,
      "predicted_price": 404.62,
      "predicted_return_pct": 0.184,
      "change_from_last_pct": -0.11
    },
    {
      "date": "2026-06-25",
      "day": 3,
      "predicted_price": 404.98,
      "predicted_return_pct": 0.091,
      "change_from_last_pct": -0.02
    },
    {
      "date": "2026-06-26",
      "day": 4,
      "predicted_price": 404.81,
      "predicted_return_pct": -0.043,
      "change_from_last_pct": -0.06
    },
    {
      "date": "2026-06-29",
      "day": 5,
      "predicted_price": 404.25,
      "predicted_return_pct": -0.138,
      "change_from_last_pct": -0.2
    }
  ],
  "recent_history": [
    {
      "date": "2026-05-08",
      "close": 428.35
    },
    {
      "date": "2026-05-11",
      "close": 445.0
    },
    {
      "date": "2026-05-12",
      "close": 433.45
    },
    {
      "date": "2026-05-13",
      "close": 445.27
    },
    {
      "date": "2026-05-14",
      "close": 443.3
    },
    {
      "date": "2026-05-15",
      "close": 422.24
    },
    {
      "date": "2026-05-18",
      "close": 409.99
    },
    {
      "date": "2026-05-19",
      "close": 404.11
    },
    {
      "date": "2026-05-20",
      "close": 417.26
    },
    {
      "date": "2026-05-21",
      "close": 417.85
    },
    {
      "date": "2026-05-22",
      "close": 426.01
    },
    {
      "date": "2026-05-26",
      "close": 433.59
    },
    {
      "date": "2026-05-27",
      "close": 440.36
    },
    {
      "date": "2026-05-28",
      "close": 442.1
    },
    {
      "date": "2026-05-29",
      "close": 435.79
    },
    {
      "date": "2026-06-01",
      "close": 415.88
    },
    {
      "date": "2026-06-02",
      "close": 423.74
    },
    {
      "date": "2026-06-03",
      "close": 423.7
    },
    {
      "date": "2026-06-04",
      "close": 418.45
    },
    {
      "date": "2026-06-05",
      "close": 391.0
    },
    {
      "date": "2026-06-08",
      "close": 408.95
    },
    {
      "date": "2026-06-09",
      "close": 396.68
    },
    {
      "date": "2026-06-10",
      "close": 381.59
    },
    {
      "date": "2026-06-11",
      "close": 399.15
    },
    {
      "date": "2026-06-12",
      "close": 406.43
    },
    {
      "date": "2026-06-15",
      "close": 411.15
    },
    {
      "date": "2026-06-16",
      "close": 404.66
    },
    {
      "date": "2026-06-17",
      "close": 396.38
    },
    {
      "date": "2026-06-18",
      "close": 400.49
    },
    {
      "date": "2026-06-22",
      "close": 405.05
    }
  ]
}